optrabot/__init__.py
optrabot/alembic.ini
optrabot/build.py
optrabot/config.py
optrabot/crud.py
optrabot/database.py
optrabot/deltaadjuster.py
optrabot/main.py
optrabot/managedtrade.py
optrabot/marketdatatype.py
optrabot/models.py
optrabot/optionhelper.py
optrabot/optrabot.py
optrabot/schemas.py
optrabot/signaldata.py
optrabot/stoplossadjuster.py
optrabot/symbolinfo.py
optrabot/timesync.py
optrabot/tradehelper.py
optrabot/trademanager.py
optrabot/traderecovery.py
optrabot/tradestatus.py
optrabot/tradinghubclient.py
optrabot/alembic/README
optrabot/alembic/env.py
optrabot/alembic/script.py.mako
optrabot/alembic/versions/235bd68ca48c_enhance_transaction_with_execution_id.py
optrabot/alembic/versions/6e910149b5a9_merge_heads_settings_table_and_template_.py
optrabot/alembic/versions/a1b2c3d4e5f6_add_trade_group_and_dates.py
optrabot/alembic/versions/b2c3d4e5f6g7_add_template_name_to_trades.py
optrabot/alembic/versions/cc3c6f4d83dc_initial_database.py
optrabot/alembic/versions/fca33d484976_add_settings_table_for_key_value_storage.py
optrabot/api/analysis.py
optrabot/api/auth.py
optrabot/api/status.py
optrabot/api/template.py
optrabot/api/trades.py
optrabot/broker/__init__.py
optrabot/broker/brokerconnector.py
optrabot/broker/brokerfactory.py
optrabot/broker/c2connector.py
optrabot/broker/c2multileg.py
optrabot/broker/ibtwsconnector.py
optrabot/broker/optionpricedata.py
optrabot/broker/order.py
optrabot/broker/spreadmonitoring.py
optrabot/broker/tastytradeconnector.py
optrabot/exceptions/__init__.py
optrabot/exceptions/orderexceptions.py
optrabot/exceptions/tradeexceptions.py
optrabot/flowengine/README.md
optrabot/flowengine/__init__.py
optrabot/flowengine/flowconfig.py
optrabot/flowengine/flowengine.py
optrabot/flowengine/flowevent.py
optrabot/tradetemplate/__init__.py
optrabot/tradetemplate/earlyexittrigger.py
optrabot/tradetemplate/templatedata.py
optrabot/tradetemplate/templatefactory.py
optrabot/tradetemplate/templatetrigger.py
optrabot-0.24.0.dist-info/METADATA
optrabot-0.24.0.dist-info/WHEEL
optrabot-0.24.0.dist-info/entry_points.txt
optrabot-0.24.0.dist-info/RECORD
