Metadata-Version: 2.4
Name: optrabot
Version: 0.24.0
Summary: QuantX OptraBot is a Options Trading Bot for automatically trading options strategies with an Interactive Brokers account.
Author: QuantX GmbH
License: MIT
Keywords: tws
Classifier: Development Status :: 4 - Beta
Classifier: Operating System :: OS Independent
Requires-Python: <3.14,>=3.13
Requires-Dist: alembic>=1.13.1
Requires-Dist: apscheduler==3.11.0
Requires-Dist: fastapi==0.117.0
Requires-Dist: httpx==0.28.1
Requires-Dist: ib-async==1.0.3
Requires-Dist: inquirerpy>=0.3.4
Requires-Dist: loguru==0.7.3
Requires-Dist: ntplib>=0.4.0
Requires-Dist: numpy<2.4.0
Requires-Dist: packaging>=24.2
Requires-Dist: pandas-market-calendars>=5.1.3
Requires-Dist: ruyaml==0.91.0
Requires-Dist: simpleeval>=0.9.13
Requires-Dist: sqlalchemy==2.0.36
Requires-Dist: tastytrade==11.0.3
Requires-Dist: tzdata>=2023.3
Requires-Dist: uvicorn==0.32.1
